examples/openapi_template.yaml
src/__init__.py
src/cli.py
src/config.py
src/converter.py
src/web_app.py
templates/index.html
openapi_converter_tool-0.1.2.dist-info/METADATA
openapi_converter_tool-0.1.2.dist-info/WHEEL
openapi_converter_tool-0.1.2.dist-info/entry_points.txt
openapi_converter_tool-0.1.2.dist-info/top_level.txt
openapi_converter_tool-0.1.2.dist-info/RECORD
