Metadata-Version: 2.4
Name: openapi-converter-tool
Version: 0.1.2
Summary: 独立的 OpenAPI 3.0.1 到项目 API 格式转换工具
Home-page: https://github.com/openapi-converter/openapi-converter
Author: OpenAPI Converter Team
Author-email: team@openapi-converter.dev
Project-URL: Bug Reports, https://github.com/openapi-converter/openapi-converter/issues
Project-URL: Source, https://github.com/openapi-converter/openapi-converter
Project-URL: Documentation, https://openapi-converter.readthedocs.io
Keywords: openapi swagger api conversion yaml
Classifier: Development Status :: 4 - Beta
Classifier: Intended Audience :: Developers
Classifier: Topic :: Software Development :: Code Generators
Classifier: Topic :: Internet :: WWW/HTTP :: HTTP Servers
Classifier: License :: OSI Approved :: MIT License
Classifier: Programming Language :: Python :: 3
Classifier: Programming Language :: Python :: 3.8
Classifier: Programming Language :: Python :: 3.9
Classifier: Programming Language :: Python :: 3.10
Classifier: Programming Language :: Python :: 3.11
Classifier: Programming Language :: Python :: 3.12
Requires-Python: >=3.8
Requires-Dist: PyYAML>=6.0
Provides-Extra: dev
Requires-Dist: pytest>=6.0; extra == "dev"
Requires-Dist: pytest-cov; extra == "dev"
Requires-Dist: black; extra == "dev"
Requires-Dist: isort; extra == "dev"
Requires-Dist: flake8; extra == "dev"
Provides-Extra: web
Requires-Dist: flask>=2.0.0; extra == "web"
Requires-Dist: werkzeug>=2.0.0; extra == "web"
Dynamic: author
Dynamic: author-email
Dynamic: classifier
Dynamic: description
Dynamic: description-content-type
Dynamic: home-page
Dynamic: keywords
Dynamic: project-url
Dynamic: provides-extra
Dynamic: requires-dist
Dynamic: requires-python
Dynamic: summary
